setup.py
ft_udacity_dist/Binomialdistribution.py
ft_udacity_dist/Gaussiandistribution.py
ft_udacity_dist/Generaldistribution.py
ft_udacity_dist/__init__.py
ft_udacity_dist.egg-info/PKG-INFO
ft_udacity_dist.egg-info/SOURCES.txt
ft_udacity_dist.egg-info/dependency_links.txt
ft_udacity_dist.egg-info/not-zip-safe
ft_udacity_dist.egg-info/top_level.txt