Metadata-Version: 1.0
Name: ft-udacity-dist
Version: 0.1
Summary: Gaussian and Binomial Distributions - Udacity Course
Home-page: UNKNOWN
Author: UNKNOWN
Author-email: UNKNOWN
License: UNKNOWN
Platform: UNKNOWN
